drawmissing.py
draw_missing-1.0.0.dist-info/LICENSE.txt
draw_missing-1.0.0.dist-info/METADATA
draw_missing-1.0.0.dist-info/WHEEL
draw_missing-1.0.0.dist-info/top_level.txt
draw_missing-1.0.0.dist-info/RECORD
