Metadata-Version: 2.1
Name: draw-missing
Version: 1.0.0
Summary: A Python package to visualize missing values in a data frame
Home-page: https://github.com/Tejas003/draw_missing
Author: Tejas Sanjay Shinde
License: MIT
Platform: UNKNOWN
Classifier: License :: OSI Approved :: MIT License
Classifier: Programming Language :: Python :: 3
Classifier: Programming Language :: Python :: 3.6
Classifier: Programming Language :: Python :: 3.7
Classifier: Operating System :: OS Independent
Requires-Dist: matplotlib
